snmpclitools/__init__.py
snmpclitools/cli/__init__.py
snmpclitools/cli/base.py
snmpclitools/cli/main.py
snmpclitools/cli/mibview.py
snmpclitools/cli/msgmod.py
snmpclitools/cli/pdu.py
snmpclitools/cli/secmod.py
snmpclitools/cli/spark.py
snmpclitools/cli/target.py
snmpclitools/error.py
snmpclitools/scripts/snmpbulkwalk.py
snmpclitools/scripts/snmpget.py
snmpclitools/scripts/snmpset.py
snmpclitools/scripts/snmptranslate.py
snmpclitools/scripts/snmptrap.py
snmpclitools/scripts/snmpwalk.py
snmpclitools-0.7.2.dist-info/LICENSE.rst
snmpclitools-0.7.2.dist-info/METADATA
snmpclitools-0.7.2.dist-info/WHEEL
snmpclitools-0.7.2.dist-info/entry_points.txt
snmpclitools-0.7.2.dist-info/RECORD
