Metadata-Version: 2.1
Name: snmpclitools
Version: 0.7.2
Summary: A collection of command-line tools for SNMP management purposes built on top of PySNMP package.
Home-page: https://github.com/lextudio/snmpclitools
License: BSD-2-Clause
Author: Ilya Etingof
Author-email: etingof@gmail.com
Requires-Python: >=3.8,<4.0
Classifier: Development Status :: 5 - Production/Stable
Classifier: Environment :: Console
Classifier: Intended Audience :: Developers
Classifier: Intended Audience :: Education
Classifier: Intended Audience :: Information Technology
Classifier: Intended Audience :: System Administrators
Classifier: Intended Audience :: Telecommunications Industry
Classifier: License :: OSI Approved :: BSD License
Classifier: Natural Language :: English
Classifier: Operating System :: OS Independent
Classifier: Programming Language :: Python :: 3
Classifier: Programming Language :: Python :: 3.8
Classifier: Programming Language :: Python :: 3.9
Classifier: Programming Language :: Python :: 3.10
Classifier: Programming Language :: Python :: 3.11
Classifier: Programming Language :: Python :: 3.12
Classifier: Topic :: Communications
Classifier: Topic :: System :: Monitoring
Classifier: Topic :: System :: Networking :: Monitoring
Requires-Dist: pysnmp (>=6.0.0,<7.0.0)
Project-URL: Repository, https://github.com/lextudio/snmpclitools
